{
  "likert_1": "Tidak langsung menggambarkan keadaan saya",
  "likert_2": "Sedikit atau jarang-jarang menggambarkan keadaan saya.",
  "likert_3": "Banyak atau kerapkali menggambarkan keadaan saya.",
  "likert_4": "Sangat banyak atau sangat kerap menggambarkan keadaan saya",
  "d1": "Saya dapati diri saya menjadi kesal/marah disebabkan perkara-perkara yang kecil.",
  "d2": "Banyak atau kerapkali menggambarkan keadaan saya.",
  "d3": "Sangat banyak atau sangat kerap menggambarkan keadaan saya",
  "d4": "Saya mengalami kesukaran bernafas (contohnya pernafasan yang laju, tercungap- cungap walaupun tidak melakukan senaman fizikal)",
  "d5": "Saya rasa diri saya tidak bergerak ke mana-mana",
  "d6": "Saya cenderung untuk bertindak keterlaluan dalam sesuatu keadaan",
  "d7": "Saya mempunyai perasaan gementar (seperti kaki menjadi lemah)",
  "d8": "Saya rasa sukar untuk relaks",
  "d9": "Saya dapati diri saya di dalam keadaan yang menjadikan saya amat risau dan menjadi tenang semula selepas ianya berakhir",
  "d10": "Saya rasa saya tidak mempunyai apa-apa untuk diharapkan",
  "d11": "Saya dapati diri saya mudah merasa kesal",
  "d12": "Saya rasa saya menggunakan banyak tenaga dalam keadaan cemas",
  "d13": "Saya rasa sedih dan murung",
  "d14": "Saya dapati diri saya hilang kesabaran sekiranya saya dilambatkan oleh sesuatu",
  "d15": "Saya rasa macam nak pengsan",
  "d16": "Saya rasa saya hilang minat dalam segala hal",
  "d17": "Saya tidak begitu berharga sebagai seorang individu",
  "d18": "Saya rasa yang saya mudah tersentuh",
  "d19": "Saya banyak berpeluh (contohnya pada tangan) walaupun bukan pada suhu tinggi atau tiada pergerakan fizikal.",
  "d20": "Saya berasa takut tanpa sebab yang munasabah",
  "d21": "Saya rasa hidup ini sudah tidak bermakna lagi",
  "d22": "Saya dapati diri saya sukar ditenteramkan",
  "d23": "Saya rasa sukar menelan",
  "d24": "Saya tidak dapat merasakan keseronokan dalam apa yang saya lakukan",
  "d25": "Saya sedar tindakbalas jantung saya walaupun tidak melakukan aktiviti fizikal",
  "d26": "Saya rasa duka dan tidak keruan",
  "d27": "Saya dapati diri saya mudah marah",
  "d28": "Saya rasa hampir-hampir menjadi panik/cemas",
  "d29": "Saya dapati sukar untuk bertenang setelah sesuatu membuatkan saya kesal",
  "d30": "Saya risau saya akan ‘dihambat’ oleh tugas yang remeh dan tidak biasa dilakukan",
  "d31": "Saya tidak bersemangat dengan apa jua yang saya lakukan",
  "d32": "Saya sukar bersabar pada gangguan terhadap perkara yang sedang saya lakukan",
  "d33": "Saya di dalam keadaan yang terlalu gementar",
  "d34": "Saya rasa diri saya langsung tidak berharga",
  "d35": "Saya hilang pertimbangan pada perkara yang menghalang saya meneruskan apa yang saya lakukan",
  "d36": "Saya rasa amat takut",
  "d37": "Saya melihat tiada masa depan untuk saya menaruh harapan",
  "d38": "Saya rasa hidup ini tidak bermakna",
  "d39": "Saya dapati diri saya semakin gelisah",
  "d40": "Saya bimbang keadaan di mana saya mungkin menjadi panik dan melakukan perkara yang membodohkan diri sendiri",
  "d41": "Saya rasa menggeletar (contohnya pada tangan)",
  "d42": "Saya sukar untuk mendapatkan semangat bagi melakukan sesuatu perkara",
  "debrief": ""
}